{
    "wallpaper": "/home/ki/.config/wpg/wallpapers/wallhaven-5gm5v8.jpg",
    "alpha": "100",

    "special": {
        "background": "#0b0603",
        "foreground": "#daccff",
        "cursor": "#daccff"
    },
    "colors": {
        "color0": "#0b0603",
        "color1": "#BA4D36",
        "color2": "#443C51",
        "color3": "#EEAC4C",
        "color4": "#572F58",
        "color5": "#9E5954",
        "color6": "#9C4F2D",
        "color7": "#a298c0",
        "color8": "#341a0b",
        "color9": "#ff5936",
        "color10": "#564472",
        "color11": "#ffe34e",
        "color12": "#79347b",
        "color13": "#dd665d",
        "color14": "#d7612d",
        "color15": "#daccff"
    }
}
