{
    "wallpaper": "/home/ki/.config/variety/Downloaded/wallhaven_River/wallhaven-lmz712.jpg",
    "alpha": "100",

    "special": {
        "background": "#0A0C0D",
        "foreground": "#ffeed8",
        "cursor": "#ffeed8"
    },
    "colors": {
        "color0": "#0A0C0D",
        "color1": "#E65A2A",
        "color2": "#5A5453",
        "color3": "#C7583F",
        "color4": "#2A464B",
        "color5": "#9E6958",
        "color6": "#9E4D36",
        "color7": "#e7bcab",
        "color8": "#1f2629",
        "color9": "#ff6c24",
        "color10": "#806560",
        "color11": "#ff6740",
        "color12": "#2f6069",
        "color13": "#dd8062",
        "color14": "#db5c38",
        "color15": "#ffeed8"
    }
}
