{
    "wallpaper": "/home/ki/.config/variety/Downloaded/wallhaven_Forest/wallhaven-yxe3lx.jpg",
    "alpha": "100",

    "special": {
        "background": "#0a0e0e",
        "foreground": "#ffe8f4",
        "cursor": "#ffe8f4"
    },
    "colors": {
        "color0": "#0a0e0e",
        "color1": "#9C612E",
        "color2": "#645250",
        "color3": "#C69466",
        "color4": "#223446",
        "color5": "#976B5D",
        "color6": "#473E48",
        "color7": "#ccb1ba",
        "color8": "#1e2b2b",
        "color9": "#d77d2e",
        "color10": "#8d615c",
        "color11": "#ffbf71",
        "color12": "#254361",
        "color13": "#d48269",
        "color14": "#634766",
        "color15": "#ffe8f4"
    }
}
