{
    "wallpaper": "/home/ki/.config/wpg/wallpapers/wallhaven-wqgy37.jpg",
    "alpha": "100",

    "special": {
        "background": "#0c1016",
        "foreground": "#d6ffff",
        "cursor": "#d6ffff"
    },
    "colors": {
        "color0": "#0c1016",
        "color1": "#A95B51",
        "color2": "#515B69",
        "color3": "#9D8776",
        "color4": "#266D8E",
        "color5": "#54768B",
        "color6": "#668EA2",
        "color7": "#a3cada",
        "color8": "#1d2736",
        "color9": "#eb6959",
        "color10": "#5d7494",
        "color11": "#ddad87",
        "color12": "#2592c4",
        "color13": "#5e9cc3",
        "color14": "#73bee3",
        "color15": "#d6ffff"
    }
}
