{
    "wallpaper": "/home/ki/.config/variety/Downloaded/wallhaven_Forest/wallhaven-qdvvp7.jpg",
    "alpha": "80",

    "special": {
        "background": "#1d211c",
        "foreground": "#fefffe",
        "cursor": "#fefffe"
    },
    "colors": {
        "color0": "#1d211c",
        "color1": "#89a8a5",
        "color2": "#80aa80",
        "color3": "#95a98e",
        "color4": "#7caa97",
        "color5": "#9eaba4",
        "color6": "#72a3a8",
        "color7": "#c6c7c6",
        "color8": "#343c32",
        "color9": "#9eeee6",
        "color10": "#93f093",
        "color11": "#b8efa4",
        "color12": "#8ef0c7",
        "color13": "#b8f3d3",
        "color14": "#81e2ec",
        "color15": "#fefffe"
    }
}
