{
    "wallpaper": "/home/ki/.config/variety/Downloaded/wallhaven_cyberspace/wallhaven-dggz63.jpg",
    "alpha": "100",

    "special": {
        "background": "#050A37",
        "foreground": "#ffe3ed",
        "cursor": "#ffe3ed"
    },
    "colors": {
        "color0": "#050A37",
        "color1": "#F60429",
        "color2": "#EC1F45",
        "color3": "#E84466",
        "color4": "#CD0125",
        "color5": "#FD728C",
        "color6": "#FD2C50",
        "color7": "#f5c5ce",
        "color8": "#081165",
        "color9": "#ff0132",
        "color10": "#ff164e",
        "color11": "#ff4479",
        "color12": "#ff012f",
        "color13": "#ff7ca7",
        "color14": "#ff255b",
        "color15": "#ffe3ed"
    }
}
